fancyutil/__init__.py
fancyutil/faded_altcolor.py
fancyutil/fancyutil.py
fancyutil-0.0.4.dist-info/licenses/LICENSE
fancyutil-0.0.4.dist-info/METADATA
fancyutil-0.0.4.dist-info/WHEEL
fancyutil-0.0.4.dist-info/top_level.txt
fancyutil-0.0.4.dist-info/RECORD
