Metadata-Version: 2.4
Name: fancyutil
Version: 0.0.4
Summary: A package designed to add a little fancy untility functions and make your life better.
Home-page: https://github.com/TaireruLLC/fancyutil
Author: Taireru LLC
Author-email: tairerullc@gmail.com
Classifier: Programming Language :: Python :: 3
Classifier: Operating System :: OS Independent
Requires-Python: >=3.6
License-File: LICENSE
Requires-Dist: mutagen
Dynamic: author
Dynamic: author-email
Dynamic: classifier
Dynamic: description
Dynamic: description-content-type
Dynamic: home-page
Dynamic: license-file
Dynamic: requires-dist
Dynamic: requires-python
Dynamic: summary
